testily/LICENSE
testily/__init__.py
testily-0.0.2.dist-info/METADATA
testily-0.0.2.dist-info/WHEEL
testily-0.0.2.dist-info/top_level.txt
testily-0.0.2.dist-info/RECORD
